andreacorreia_dundie-0.1.0.dist-info/licenses/LICENSE
dundie/__init__.py
dundie/__main__.py
dundie/cli.py
dundie/core.py
dundie/database.py
dundie/settings.py
dundie/utils/__init__.py
dundie/utils/email.py
dundie/utils/log.py
dundie/utils/user.py
tests/__init__.py
tests/add_read.py
tests/constants.py
tests/test_add.py
tests/test_database.py
tests/test_load.py
tests/test_utils.py
andreacorreia_dundie-0.1.0.dist-info/METADATA
andreacorreia_dundie-0.1.0.dist-info/WHEEL
andreacorreia_dundie-0.1.0.dist-info/entry_points.txt
andreacorreia_dundie-0.1.0.dist-info/top_level.txt
andreacorreia_dundie-0.1.0.dist-info/RECORD
