Metadata-Version: 2.4
Name: andreacorreia-dundie
Version: 0.1.0
Summary: Reward Point System for Dunder Mifflin
Author: Andrea Correia
Requires-Python: >=3.8
License-File: LICENSE
Requires-Dist: click
Requires-Dist: rich
Requires-Dist: rich-click
Provides-Extra: test
Requires-Dist: pytest; extra == "test"
Requires-Dist: pytest-forked; extra == "test"
Requires-Dist: flake8; extra == "test"
Requires-Dist: pyproject-flake8; extra == "test"
Requires-Dist: black; extra == "test"
Requires-Dist: isort; extra == "test"
Provides-Extra: dev
Requires-Dist: ipython; extra == "dev"
Requires-Dist: ipdb; extra == "dev"
Requires-Dist: pytest-watch; extra == "dev"
Requires-Dist: pytest; extra == "dev"
Requires-Dist: flake8; extra == "dev"
Requires-Dist: pyproject-flake8; extra == "dev"
Requires-Dist: black; extra == "dev"
Requires-Dist: isort; extra == "dev"
Requires-Dist: mkdocs; extra == "dev"
Requires-Dist: wheel; extra == "dev"
Dynamic: author
Dynamic: description
Dynamic: description-content-type
Dynamic: license-file
Dynamic: provides-extra
Dynamic: requires-dist
Dynamic: requires-python
Dynamic: summary
